stochastic_lasso/__init__.py
stochastic_lasso/glmnet_model.py
stochastic_lasso/stochastic_lasso.py
stochastic_lasso/util.py
stochastic_lasso-0.0.1.dist-info/METADATA
stochastic_lasso-0.0.1.dist-info/WHEEL
stochastic_lasso-0.0.1.dist-info/top_level.txt
stochastic_lasso-0.0.1.dist-info/RECORD
